edxval/__init__.py
edxval/admin.py
edxval/api.py
edxval/exceptions.py
edxval/models.py
edxval/serializers.py
edxval/transcript_utils.py
edxval/urls.py
edxval/utils.py
edxval/views.py
edxval/wsgi.py
edxval/config/__init__.py
edxval/config/waffle.py
edxval/migrations/0001_squashed_0016_add_transcript_credentials_model.py
edxval/migrations/0002_add_error_description_field.py
edxval/migrations/0003_delete_transcriptcredentials.py
edxval/migrations/0004_add_edx_ai_translations_provider.py
edxval/migrations/__init__.py
edxval/tests/__init__.py
edxval/tests/constants.py
edxval/tests/test_admin.py
edxval/tests/test_api.py
edxval/tests/test_models.py
edxval/tests/test_serializers.py
edxval/tests/test_storages.py
edxval/tests/test_transcript_utils.py
edxval/tests/test_utils.py
edxval/tests/test_views.py
edxval-3.1.0.dist-info/licenses/LICENSE
edxval-3.1.0.dist-info/METADATA
edxval-3.1.0.dist-info/WHEEL
edxval-3.1.0.dist-info/top_level.txt
edxval-3.1.0.dist-info/RECORD
