Metadata-Version: 2.4
Name: edxval
Version: 3.1.0
Summary: edx-val
Home-page: http://github.com/openedx/edx-val
Author: edX
License: AGPL
Classifier: Development Status :: 5 - Production/Stable
Classifier: Intended Audience :: Developers
Classifier: License :: OSI Approved :: GNU Affero General Public License v3
Classifier: Operating System :: OS Independent
Classifier: Programming Language :: Python
Classifier: Programming Language :: Python :: 3
Classifier: Programming Language :: Python :: 3.11
Classifier: Programming Language :: Python :: 3.12
Classifier: Framework :: Django
Classifier: Framework :: Django :: 4.2
Classifier: Framework :: Django :: 5.2
License-File: LICENSE
Requires-Dist: Django
Requires-Dist: cachetools
Requires-Dist: django-model-utils
Requires-Dist: django-storages
Requires-Dist: edx-django-release-util
Requires-Dist: edx-drf-extensions
Requires-Dist: edx-toggles>=2.0.0
Requires-Dist: lxml
Requires-Dist: pillow
Requires-Dist: pysrt
Dynamic: author
Dynamic: classifier
Dynamic: description
Dynamic: description-content-type
Dynamic: home-page
Dynamic: license
Dynamic: license-file
Dynamic: requires-dist
Dynamic: summary
